githubAPy/__init__.py
githubAPy/wrapper.py
githubAPy-0.4.dist-info/METADATA
githubAPy-0.4.dist-info/RECORD
githubAPy-0.4.dist-info/WHEEL
githubAPy-0.4.dist-info/top_level.txt
