Metadata-Version: 2.1
Name: githubAPy
Version: 0.4
Summary: Python wrapper to easily communicate with the GitHub API
Home-page: https://github.com/techytushar/githubAPy
Author: Tushar Mittal
Author-email: chiragmittal.mittal@gmail.com
License: GNU General Public License v3 (GPLv3)
Keywords: github api python wrapper
Platform: UNKNOWN
Classifier: Development Status :: 4 - Beta
Classifier: Intended Audience :: Developers
Classifier: License :: OSI Approved :: GNU General Public License v3 (GPLv3)
Classifier: Programming Language :: Python :: 3
Requires-Dist: requests
